pre_commit_hook_poetry_auto_semver/__init__.py
pre_commit_hook_poetry_auto_semver/poetry_auto_semver.py
pre_commit_hook_poetry_auto_semver-0.0.3.dist-info/entry_points.txt
pre_commit_hook_poetry_auto_semver-0.0.3.dist-info/LICENSE
pre_commit_hook_poetry_auto_semver-0.0.3.dist-info/METADATA
pre_commit_hook_poetry_auto_semver-0.0.3.dist-info/WHEEL
pre_commit_hook_poetry_auto_semver-0.0.3.dist-info/RECORD
