Metadata-Version: 2.1
Name: pre_commit_hook_poetry_auto_semver
Version: 0.0.3
Summary: 
Author: Ian Pearthree
Author-email: 52967928+ipear3@users.noreply.github.com
Requires-Python: >=3.11,<4.0
Classifier: Programming Language :: Python :: 3
Classifier: Programming Language :: Python :: 3.11
Requires-Dist: pre-commit (>=3.4.0,<4.0.0)
Requires-Dist: semver (>=3.0.1,<4.0.0)
